<?xml version="1.0" encoding="utf-8"?>
<odoo>
    <data>
        <record id="op_course_23" model="op.course">
            <field name="code">bca</field>
            <field name="name">Bachelor of computer Applications</field>
            <field name="evaluation_type">GPA</field>
            <field name="section">Degree Course</field>
            <field name="reg_fees">True</field>
            <field name="product_id" ref="op_product_23"/>
            <field name="fees_term_id" ref="openeducat_fees.op_fees_term_1"/>
        </record>
    </data>
</odoo>